testdoc/__about__.py
testdoc/__init__.py
testdoc/__main__.py
testdoc/cli.py
testdoc/default.toml
testdoc/testdoc.py
testdoc/helper/cliargs.py
testdoc/helper/datetimeconverter.py
testdoc/helper/logger.py
testdoc/helper/pathconverter.py
testdoc/helper/toml_reader.py
testdoc/html/images/robotframework.svg
testdoc/html/rendering/render.py
testdoc/html/templates/v1/jinja_template_01.html
testdoc/html/templates/v1/jinja_template_02.html
testdoc/html/templates/v2/jinja_template_03.html
testdoc/html/themes/__init__.py
testdoc/html/themes/theme_config.py
testdoc/html/themes/themes.py
testdoc/parser/testcaseparser.py
testdoc/parser/testsuiteparser.py
testdoc/parser/modifier/sourceprefixmodifier.py
testdoc/parser/modifier/suitefilemodifier.py
robotframework_testdoc-0.3.0.dist-info/METADATA
robotframework_testdoc-0.3.0.dist-info/WHEEL
robotframework_testdoc-0.3.0.dist-info/entry_points.txt
robotframework_testdoc-0.3.0.dist-info/licenses/LICENSE
robotframework_testdoc-0.3.0.dist-info/RECORD
