Metadata-Version: 2.4
Name: robotframework-testdoc
Version: 0.3.0
Summary: A CLI Tool to generate a Test Documentation for your RobotFramework Test Scripts.
Project-URL: Repository, https://github.com/MarvKler/robotframework-testdoc
Project-URL: Issues, https://github.com/MarvKler/robotframework-testdoc/issues
Author-email: Marvin Klerx <marvinklerx20@gmail.com>
License: Apache-2.0
License-File: LICENSE
Classifier: Development Status :: 4 - Beta
Classifier: Programming Language :: Python
Classifier: Programming Language :: Python :: 3.9
Classifier: Programming Language :: Python :: 3.10
Classifier: Programming Language :: Python :: 3.11
Classifier: Programming Language :: Python :: 3.12
Requires-Python: >=3.9
Requires-Dist: click
Requires-Dist: jinja2
Requires-Dist: robotframework
Requires-Dist: tomli
Provides-Extra: dev
Requires-Dist: hatch; extra == 'dev'
Requires-Dist: mypy; extra == 'dev'
Requires-Dist: pre-commit; extra == 'dev'
Requires-Dist: pytest; extra == 'dev'
Requires-Dist: robotframework-robocop; extra == 'dev'
Requires-Dist: ruff; extra == 'dev'
